mini3di/__init__.py
mini3di/_unkerasify.py
mini3di/encoder.py
mini3di/encoder_weights_3di.kerasify
mini3di/layers.py
mini3di/py.typed
mini3di/utils.py
mini3di-0.2.1.dist-info/COPYING
mini3di-0.2.1.dist-info/METADATA
mini3di-0.2.1.dist-info/WHEEL
mini3di-0.2.1.dist-info/top_level.txt
mini3di-0.2.1.dist-info/zip-safe
mini3di-0.2.1.dist-info/RECORD
