Metadata-Version: 2.1
Name: mini3di
Version: 0.2.1
Summary: A NumPy port of the foldseek code for encoding structures to 3di.
Home-page: https://github.com/althonos/mini3di
Author: Martin Larralde
Author-email: martin.larralde@embl.de
License: BSD-3-Clause
Project-URL: Bug Tracker, https://github.com/althonos/mini3di/issues
Project-URL: Changelog, https://github.com/althonos/mini3di/blob/master/CHANGELOG.md
Project-URL: Coverage, https://codecov.io/gh/althonos/mini3di/
Project-URL: Builds, https://github.com/althonos/mini3di/actions
Project-URL: PyPI, https://pypi.org/project/mini3di
Keywords: bioinformatics,protein,structure,foldseek,3di
Platform: posix
Classifier: Development Status :: 4 - Beta
Classifier: Intended Audience :: Developers
Classifier: Intended Audience :: Science/Research
Classifier: License :: OSI Approved :: BSD License
Classifier: Operating System :: OS Independent
Classifier: Programming Language :: Python :: 3.7
Classifier: Programming Language :: Python :: 3.8
Classifier: Programming Language :: Python :: 3.9
Classifier: Programming Language :: Python :: 3.10
Classifier: Programming Language :: Python :: 3.11
Classifier: Programming Language :: Python :: 3.12
Classifier: Topic :: Scientific/Engineering :: Bio-Informatics
Classifier: Topic :: Scientific/Engineering :: Medical Science Apps.
Classifier: Typing :: Typed
Requires-Python: >=3.7
License-File: COPYING
Requires-Dist: numpy
Requires-Dist: importlib-resources>=1.3; python_version < "3.9"
